pydantic_settings_sources/__init__.py
pydantic_settings_sources/errors.py
pydantic_settings_sources/sources.py
pydantic_settings_sources/utils.py
pydantic_settings_extra_sources-0.1.0.dist-info/METADATA
pydantic_settings_extra_sources-0.1.0.dist-info/WHEEL
pydantic_settings_extra_sources-0.1.0.dist-info/licenses/LICENSE
pydantic_settings_extra_sources-0.1.0.dist-info/RECORD
