Metadata-Version: 2.4
Name: pydantic-settings-extra-sources
Version: 0.1.0
Summary: Extra sources for pydantic-settings with environment variable substitution for YAML and TOML files
License: MIT
License-File: LICENSE
Keywords: pydantic,settings,yaml,toml,environment,config,configuration
Author: LazyTrot
Author-email: admin@lazytrot.dev
Requires-Python: >=3.8,<4.0
Classifier: Development Status :: 4 - Beta
Classifier: Intended Audience :: Developers
Classifier: License :: OSI Approved :: MIT License
Classifier: Programming Language :: Python :: 3
Classifier: Programming Language :: Python :: 3.8
Classifier: Programming Language :: Python :: 3.9
Classifier: Programming Language :: Python :: 3.10
Classifier: Programming Language :: Python :: 3.11
Classifier: Programming Language :: Python :: 3.12
Classifier: Programming Language :: Python :: 3.13
Classifier: Programming Language :: Python :: 3.14
Classifier: Topic :: Software Development :: Libraries :: Python Modules
Requires-Dist: deepmerge (>=1.1.0)
Requires-Dist: pydantic (>=1.10)
Requires-Dist: pydantic-settings (>=1.0)
Requires-Dist: pyyaml (>=6.0)
Requires-Dist: toml (>=0.10.2)
